mapuche/__init__.py
mapuche/__main__.py
mapuche/mapuche.py
mapuche/models.py
mapuche/parser.py
mapuche/styles.py
mapuche/tree_table.py
mapuche-1.0.3.dist-info/LICENSE
mapuche-1.0.3.dist-info/METADATA
mapuche-1.0.3.dist-info/WHEEL
mapuche-1.0.3.dist-info/entry_points.txt
mapuche-1.0.3.dist-info/top_level.txt
mapuche-1.0.3.dist-info/RECORD
