Metadata-Version: 2.2
Name: mapuche
Version: 1.0.3
Summary: Linker's map file browser
Author-email: Alexey Lapshin <alexeyfonlapshin@gmail.com>
License: MIT
Keywords: map,elf,linker
Classifier: Programming Language :: Python :: 3
Requires-Python: >=3.6
License-File: LICENSE
Requires-Dist: textual==0.85.1
